MANIFEST.in
README.md
setup.py
rtcshare/RtcshareContext.py
rtcshare/__init__.py
rtcshare/cli.py
rtcshare/handle_request.py
rtcshare/handle_video_query.py
rtcshare/handle_zarr_query.py
rtcshare/start.py
rtcshare.egg-info/PKG-INFO
rtcshare.egg-info/SOURCES.txt
rtcshare.egg-info/dependency_links.txt
rtcshare.egg-info/entry_points.txt
rtcshare.egg-info/requires.txt
rtcshare.egg-info/top_level.txt
rtcshare/js/package-lock.json
rtcshare/js/package.json
rtcshare/js/tsconfig.json
rtcshare/js/src/ConnectorHttpProxyTypes.ts
rtcshare/js/src/DirManager.ts
rtcshare/js/src/OutgoingProxyConnection.ts
rtcshare/js/src/RemotePeer.ts
rtcshare/js/src/RtcsharePeerRequest.ts
rtcshare/js/src/RtcshareRequest.ts
rtcshare/js/src/Server.ts
rtcshare/js/src/ServiceManager.ts
rtcshare/js/src/SignalCommunicator.ts
rtcshare/js/src/WebsocketMessage.ts
rtcshare/js/src/createMessageWithBinaryPayload.ts
rtcshare/js/src/getIceServers.ts
rtcshare/js/src/handleApiRequest.ts
rtcshare/js/src/handleServiceQueryRequest.ts
rtcshare/js/src/index.ts
rtcshare/js/src/validateObject.ts
rtcshare/js/src/wrtc.d.ts