Metadata-Version: 2.1
Name: rtcshare
Version: 0.1.6
Summary: Share a directory and resources with the browser and with remote computers. For use with Figurl.
Home-page: https://github.com/scratchrealm/rtcshare
Author: Jeremy Magland
Author-email: jmagland@flatironinstitute.org
